Metadata-Version: 1.0
Name: bhz-stats
Version: 0.1
Summary: Gaussian and Binomial distributions
Home-page: UNKNOWN
Author: Behnaz Sadat
Author-email: ssadat2@asu.edu
License: UNKNOWN
Platform: UNKNOWN
